hammertime/__init__.py
hammertime/__version__.py
hammertime/config.py
hammertime/core.py
hammertime/http.py
hammertime/kb.py
hammertime/requestscheduler.py
hammertime/ruleset.py
hammertime/engine/__init__.py
hammertime/engine/aiohttp.py
hammertime/engine/interface.py
hammertime/engine/retry.py
hammertime/engine/scaling.py
hammertime/rules/__init__.py
hammertime/rules/behavior.py
hammertime/rules/body.py
hammertime/rules/deadhostdetection.py
hammertime/rules/filterrequestfromurl.py
hammertime/rules/header.py
hammertime/rules/redirects.py
hammertime/rules/sampling.py
hammertime/rules/simhash.py
hammertime/rules/status.py
hammertime/rules/timeout.py
hammertime/rules/waf.py
hammertime/utils/har.py
HammerTime_http-0.10.1.dist-info/LICENSE.md
HammerTime_http-0.10.1.dist-info/METADATA
HammerTime_http-0.10.1.dist-info/WHEEL
HammerTime_http-0.10.1.dist-info/top_level.txt
HammerTime_http-0.10.1.dist-info/RECORD
